{
  "Learning": {
    "name": "Learning",
    "description": "Represents information that defines a training that can be made available as a course, program, or on-site experience, for a contact.",
    "properties": {
      "AcademicLevel": {
        "type": "picklist",
        "description": "The applicable point in the education process."
      },
      "ActiveFromDate": {
        "type": "date",
        "description": "Date the Learning framework became active."
      },
      "ActiveToDate": {
        "type": "date",
        "description": "Date the Learning framework became inactive."
      },
      "Category": {
        "type": "multipicklist",
        "description": "Specifies the category of the learning."
      },
      "CipCode": {
        "type": "string",
        "description": "Classification of Instructional Programming code that identifies the program or field of study."
      },
      "Description": {
        "type": "textarea",
        "description": "Description of the Learning framework."
      },
      "Duration": {
        "type": "double",
        "description": "The allocated length of time for completion of the Learning."
      },
      "DurationUnit": {
        "type": "picklist",
        "description": "The unit of measurement for the length of time for completion."
      },
      "Format": {
        "type": "multipicklist",
        "description": "Specifies the format in which the learning is offered."
      },
      "Grade": {
        "type": "multipicklist",
        "description": "Specifies the grade of the learning."
      },
      "ImageUrl": {
        "type": "url",
        "description": "The URL to an image for the learning."
      },
      "IsActive": {
        "type": "boolean",
        "description": "Specifies that the Learning framework is active."
      },
      "IsLocked": {
        "type": "boolean",
        "description": "Indicates whether the record is locked (true) or not (false)."
      },
      "LastReferencedDate": {
        "type": "dateTime",
        "description": "The timestamp when the current user last accessed this record, a record related to this record, or a list view."
      },
      "LastViewedDate": {
        "type": "dateTime",
        "description": "The timestamp when the current user last viewed this record or list view. If this value is null, the user might have only accessed this record or list view (LastReferencedDate) but not viewed it."
      },
      "MayEdit": {
        "type": "boolean",
        "description": "Indicates whether the record can be edited (true) or not (false)."
      },
      "Name": {
        "type": "string",
        "description": "Name of the Learning framework."
      },
      "OwnerId": {
        "type": "reference",
        "description": "The user who owns this record."
      },
      "ProviderId": {
        "type": "reference",
        "description": "Account of the institution that provides the Learning."
      },
      "Type": {
        "type": "picklist",
        "description": "Specifies the type of Learning."
      }
    },
    "module": "Education Cloud",
    "sourceUrl": "https://developer.salesforce.com/docs/atlas.en-us.edu_cloud_dev_guide.meta/edu_cloud_dev_guide/sforce_api_objects_learning.htm"
  }
}