{
  "BotVersion": {
    "name": "BotVersion",
    "description": "Represents a version of a bot or agent defined by a BotDefinition record.",
    "properties": {
      "BotDefinitionId": {
        "type": "reference",
        "description": "Required. This field relates a bot version to its parent BotDefinition record."
      },
      "CopilotPrimaryLanguage": {
        "type": "picklist",
        "description": "The primary language that the bot or agent communicates in."
      },
      "CopilotSecondaryLanguages": {
        "type": "string",
        "description": "A comma-separated list of additional languages that the bot or agent supports."
      },
      "DeveloperName": {
        "type": "string",
        "description": "The unique name for this object."
      },
      "Status": {
        "type": "picklist",
        "description": "Required. Indicates whether the bot version is active or inactive. Only one version for a related BotDefinition can be active at once."
      },
      "ToneType": {
        "type": "picklist",
        "description": "Defines the tone of the bot."
      },
      "VersionNumber": {
        "type": "int",
        "description": "The number for this version of the bot or agent."
      }
    },
    "module": "Core Salesforce",
    "sourceUrl": "https://developer.salesforce.com/docs/atlas.en-us.object_reference.meta/object_reference/sforce_api_objects_botversion.htm",
    "clouds": [
      "Core Salesforce"
    ]
  }
}