{
  "BusinessAlertStatus": {
    "name": "BusinessAlertStatus",
    "description": "Represents information about the read status of an insight alert.",
    "properties": {
      "BusinessAlertId": {
        "type": "reference",
        "description": "The insight alert related to the status."
      },
      "IsAlertRead": {
        "type": "boolean",
        "description": "Indicates whether the insight alert is read by the user (true) or not (false)."
      },
      "Name": {
        "type": "string",
        "description": "Specifies the activation status of the insight alert."
      },
      "UserId": {
        "type": "reference",
        "description": "The ID of the user who is associated with the alert."
      }
    },
    "module": "Core Salesforce",
    "sourceUrl": "https://developer.salesforce.com/docs/atlas.en-us.object_reference.meta/object_reference/sforce_api_objects_businessalertstatus.htm"
  }
}