{
  "CaseContactRole": {
    "name": "CaseContactRole",
    "description": "Represents the role that a given Contact plays on a Case.",
    "properties": {
      "CasesId": {
        "type": "reference",
        "description": "ID of the cases associated with this contact."
      },
      "ContactId": {
        "type": "reference",
        "description": "Required. ID of the contact."
      },
      "IsDeleted": {
        "type": "boolean",
        "description": "Indicates whether the object has been moved to the Recycle Bin (true) or not (false). Label is Deleted."
      },
      "Role": {
        "type": "picklist",
        "description": "Name of the role played by the contact on this case, such as Technical Contact, Business Contact, Decision Maker, and so on. Must be unique—there can't be multiple records in which the CaseId, ContactId , and Role values are identical. Different contacts can play the same role on the same case. A contact can play different roles on the same case."
      }
    },
    "module": "Core Salesforce"
  }
}