{
  "Competency": {
    "name": "Competency",
    "description": "Represents a skill, subject matter expertise, or behavior required for a job or role.",
    "properties": {
      "Category": {
        "type": "picklist",
        "description": "Specifies the category of the competency."
      },
      "Description": {
        "type": "textarea",
        "description": "The description of the competency."
      },
      "LastReferencedDate": {
        "type": "dateTime",
        "description": "The timestamp for when the current user last viewed a record related to this record."
      },
      "LastViewedDate": {
        "type": "dateTime",
        "description": "The timestamp for when the current user last viewed this record. If this value is null, it’s possible that this record was referenced (LastReferencedDate) and not viewed."
      },
      "Name": {
        "type": "string",
        "description": "The name of the competency."
      },
      "OwnerId": {
        "type": "reference",
        "description": "ID of the user who created the record."
      }
    },
    "module": "Public Sector Cloud"
  }
}