{
  "AnalyticsWorkspaceAsset": {
    "name": "AnalyticsWorkspaceAsset",
    "description": "Represents a Tableau Next asset in a workspace.",
    "properties": {
      "ActivePromotionRequestId": {
        "type": "reference",
        "description": "The ID of the active promotion request for the workspace asset."
      },
      "AnalyticsWorkspaceId": {
        "type": "reference",
        "description": "The ID of the Tableau Next workspace the asset is associated with."
      },
      "AssetId": {
        "type": "reference",
        "description": "The ID of the asset."
      },
      "AssetType": {
        "type": "picklist",
        "description": "The type of asset."
      },
      "AssetUsageType": {
        "type": "picklist",
        "description": "The type of usage for the asset."
      },
      "HistoricalPromotionStatus": {
        "type": "picklist",
        "description": "The historical promotion status for the asset."
      },
      "MetadataSourceType": {
        "type": "picklist",
        "description": "The source type of the asset metadata."
      }
    },
    "module": "Core Salesforce",
    "sourceUrl": "https://developer.salesforce.com/docs/atlas.en-us.object_reference.meta/object_reference/sforce_api_objects_analyticsworkspaceasset.htm",
    "clouds": [
      "Core Salesforce"
    ]
  }
}