{
  "AutomatedActionOverride": {
    "name": "AutomatedActionOverride",
    "description": "Represents a modified attribute of a shared automated action. For example, the modified attribute can contain customizations for your business.",
    "properties": {
      "FieldName": {
        "type": "string",
        "description": "The name of the field to override."
      },
      "IsLocked": {
        "type": "boolean",
        "description": "Indicates whether the automated action override record is locked or not."
      },
      "IsRelatedRecordOverridable": {
        "type": "boolean",
        "description": "Indicates whether the parent automated action record can be overridden."
      },
      "MayEdit": {
        "type": "boolean",
        "description": "Indicates whether the automated action override record can be edited or not."
      },
      "Name": {
        "type": "string",
        "description": "Name of the automated action."
      },
      "RelatedRecordApiName": {
        "type": "string",
        "description": "The object name of the RelatedRecordId."
      },
      "RelatedRecordId": {
        "type": "reference",
        "description": "ID of the automated action."
      },
      "Value": {
        "type": "textarea",
        "description": "The overridden value used for FieldName."
      }
    },
    "module": "Core Salesforce",
    "sourceUrl": "https://developer.salesforce.com/docs/atlas.en-us.object_reference.meta/object_reference/sforce_api_objects_automatedactionoverride.htm",
    "clouds": [
      "Core Salesforce"
    ]
  }
}