{
  "OrderChangeLog": {
    "name": "OrderChangeLog",
    "description": "Represents a log record of all change requests made to an order post activation. A log record is always one-to-one to change an order request.",
    "properties": {
      "ChangeLineId": {
        "type": "reference",
        "description": "The ID of the main change line created as a result of the change request. For example, if you change an order item, the ChangeLineId would be the change OrderItem ID, or if you change a shipping address, the ChangeLineId would be the change OrderDeliveryGroup ID."
      },
      "ChangeLineType": {
        "type": "picklist",
        "description": "The method used to implement the change."
      },
      "ChangeOrderId": {
        "type": "reference",
        "description": "The ID of the change order."
      },
      "ChangeRequest": {
        "type": "string",
        "description": "The unique ID of the request of which this change is a part."
      },
      "ChangeSummary": {
        "type": "textarea",
        "description": "A human-readable summary of the change details."
      },
      "ChangeType": {
        "type": "picklist",
        "description": "The type of the change request."
      },
      "CurrencyIsoCode": {
        "type": "picklist",
        "description": "The ISO code for any currency allowed by the organization."
      },
      "Name": {
        "type": "string",
        "description": "The name for the order change log."
      },
      "RelatedLineId": {
        "type": "reference",
        "description": "The ID of the main line that is changed as a result of this change."
      },
      "RelatedOrderId": {
        "type": "reference",
        "description": "The ID of the order that is changed."
      },
      "Status": {
        "type": "picklist",
        "description": "The order status of the change order."
      }
    },
    "module": "Core Salesforce"
  }
}