{
  "TaskPriority": {
    "name": "TaskPriority",
    "description": "Represents the importance or urgency of a task, such as High, Normal, or Low.",
    "properties": {
      "ApiName": {
        "type": "string",
        "description": "Uniquely identifies a picklist value so it can be retrieved without using an ID or master label.",
        "maxLength": 255,
        "nullable": false,
        "readOnly": true
      },
      "IsDefault": {
        "type": "boolean",
        "description": "Indicates whether the status is the default task priority value (true) or not (false) in the picklist. Only one value in the picklist can be the default value.",
        "nullable": false,
        "readOnly": true
      },
      "IsHighPriority": {
        "type": "boolean",
        "description": "Indicates whether this task priority value represents a high priority task (true) or not (false). Multiple task priority values can represent a high-priority task.",
        "nullable": false,
        "readOnly": true
      },
      "MasterLabel": {
        "type": "string",
        "description": "Master label for this task priority value. This display value is the internal label that doesn’t get translated. Limit: 255 characters.",
        "maxLength": 255,
        "nullable": true,
        "readOnly": true
      },
      "SortOrder": {
        "type": "int",
        "description": "Number used to sort this value in the task priority picklist. These numbers aren’t guaranteed to be sequential, as some previous task priority values might have been deleted.",
        "nullable": true,
        "readOnly": true
      },
      "Id": {
        "type": "string",
        "description": "Task Priority Value ID",
        "format": "salesforce-id",
        "maxLength": 18,
        "nullable": false,
        "readOnly": true
      },
      "CreatedById": {
        "type": "string",
        "description": "Created By ID",
        "format": "salesforce-id",
        "x-object": "User",
        "maxLength": 18,
        "nullable": false,
        "readOnly": true
      },
      "CreatedDate": {
        "type": "string",
        "description": "Created Date",
        "format": "date-time",
        "nullable": false,
        "readOnly": true
      },
      "LastModifiedById": {
        "type": "string",
        "description": "Last Modified By ID",
        "format": "salesforce-id",
        "x-object": "User",
        "maxLength": 18,
        "nullable": false,
        "readOnly": true
      },
      "LastModifiedDate": {
        "type": "string",
        "description": "Last Modified Date",
        "format": "date-time",
        "nullable": false,
        "readOnly": true
      },
      "SystemModstamp": {
        "type": "string",
        "description": "System Modstamp",
        "format": "date-time",
        "nullable": false,
        "readOnly": true
      }
    },
    "module": "Core Salesforce",
    "sourceUrl": "https://developer.salesforce.com/docs/atlas.en-us.object_reference.meta/object_reference/sforce_api_objects_taskpriority.htm",
    "createable": false,
    "updateable": false,
    "deletable": false,
    "queryable": true,
    "searchable": false
  }
}