{
  "Territory2": {
    "name": "Territory2",
    "description": "Territories - Territory2",
    "properties": {
      "Id": {
        "type": "string",
        "description": "Territory ID",
        "format": "salesforce-id",
        "maxLength": 18,
        "nullable": false,
        "readOnly": true
      },
      "Name": {
        "type": "string",
        "description": "Territory Label",
        "maxLength": 80,
        "nullable": false
      },
      "Territory2TypeId": {
        "type": "string",
        "description": "Territory Type ID",
        "format": "salesforce-id",
        "x-object": "Territory2Type",
        "maxLength": 18,
        "nullable": false
      },
      "Territory2ModelId": {
        "type": "string",
        "description": "Territory Model ID",
        "format": "salesforce-id",
        "x-object": "Territory2Model",
        "maxLength": 18,
        "nullable": false,
        "readOnly": true
      },
      "ParentTerritory2Id": {
        "type": "string",
        "description": "Parent Territory ID",
        "format": "salesforce-id",
        "x-object": "Territory2",
        "maxLength": 18,
        "nullable": true
      },
      "Description": {
        "type": "string",
        "description": "Territory Description",
        "maxLength": 1000,
        "nullable": true
      },
      "ForecastUserId": {
        "type": "string",
        "description": "User ID",
        "format": "salesforce-id",
        "x-object": "User",
        "maxLength": 18,
        "nullable": true
      },
      "AccountAccessLevel": {
        "type": "string",
        "description": "Account Access Level",
        "format": "enum",
        "enum": [
          "Read",
          "Edit",
          "All"
        ],
        "maxLength": 40,
        "nullable": false
      },
      "OpportunityAccessLevel": {
        "type": "string",
        "description": "Opportunity Access Level",
        "format": "enum",
        "enum": [
          "None",
          "Read",
          "Edit"
        ],
        "maxLength": 40,
        "nullable": false
      },
      "CaseAccessLevel": {
        "type": "string",
        "description": "Case Access Level",
        "format": "enum",
        "enum": [
          "None",
          "Read",
          "Edit"
        ],
        "maxLength": 40,
        "nullable": false
      },
      "ContactAccessLevel": {
        "type": "string",
        "description": "Contact Access Level",
        "format": "enum",
        "enum": [
          "None",
          "Read",
          "Edit"
        ],
        "maxLength": 40,
        "nullable": false,
        "readOnly": true
      },
      "LastModifiedDate": {
        "type": "string",
        "description": "Last Modified Date",
        "format": "date-time",
        "nullable": false,
        "readOnly": true
      },
      "LastModifiedById": {
        "type": "string",
        "description": "Last Modified By ID",
        "format": "salesforce-id",
        "x-object": "User",
        "maxLength": 18,
        "nullable": false,
        "readOnly": true
      },
      "SystemModstamp": {
        "type": "string",
        "description": "System Modstamp",
        "format": "date-time",
        "nullable": false,
        "readOnly": true
      },
      "DeveloperName": {
        "type": "string",
        "description": "Developer Name",
        "maxLength": 80,
        "nullable": false
      }
    },
    "module": "N/A",
    "keyPrefix": "0MI",
    "label": "Territory",
    "sourceUrl": "https://developer.salesforce.com/docs/atlas.en-us.object_reference.meta/object_reference/",
    "createable": true,
    "updateable": true,
    "deletable": true,
    "queryable": true,
    "searchable": false,
    "childRelationships": [
      {
        "childObject": "AccountUserTerritory2View",
        "field": "Territory2Id",
        "relationshipName": "AccountUserTerritory2Views",
        "cascadeDelete": false
      },
      {
        "childObject": "ForecastingAdjustment",
        "field": "Territory2Id",
        "relationshipName": null,
        "cascadeDelete": false
      },
      {
        "childObject": "ForecastingFact",
        "field": "Territory2Id",
        "relationshipName": null,
        "cascadeDelete": false
      },
      {
        "childObject": "ForecastingItem",
        "field": "Territory2Id",
        "relationshipName": null,
        "cascadeDelete": false
      },
      {
        "childObject": "ForecastingOwnerAdjustment",
        "field": "Territory2Id",
        "relationshipName": null,
        "cascadeDelete": false
      },
      {
        "childObject": "ForecastingQuota",
        "field": "Territory2Id",
        "relationshipName": null,
        "cascadeDelete": false
      },
      {
        "childObject": "ForecastingShare",
        "field": "SharedForecastManagerRoleId",
        "relationshipName": null,
        "cascadeDelete": true
      },
      {
        "childObject": "Group",
        "field": "RelatedId",
        "relationshipName": null,
        "cascadeDelete": false
      },
      {
        "childObject": "ObjectTerritory2Association",
        "field": "Territory2Id",
        "relationshipName": "ObjectTerritory2Associations",
        "cascadeDelete": true
      },
      {
        "childObject": "Opportunity",
        "field": "Territory2Id",
        "relationshipName": null,
        "cascadeDelete": false
      },
      {
        "childObject": "OpportunityChangeEvent",
        "field": "Territory2Id",
        "relationshipName": null,
        "cascadeDelete": false
      },
      {
        "childObject": "RuleTerritory2Association",
        "field": "Territory2Id",
        "relationshipName": "RuleTerritory2Associations",
        "cascadeDelete": true
      },
      {
        "childObject": "SurveySubject",
        "field": "SubjectId",
        "relationshipName": "SurveySubjectEntities",
        "cascadeDelete": false
      },
      {
        "childObject": "Territory2",
        "field": "ParentTerritory2Id",
        "relationshipName": null,
        "cascadeDelete": false
      },
      {
        "childObject": "UserTerritory2Association",
        "field": "Territory2Id",
        "relationshipName": "UserTerritory2Associations",
        "cascadeDelete": true
      }
    ]
  }
}