{
  "Layout": {
    "name": "Layout",
    "label": "Layout",
    "description": "Represents Layout metadata component used in Salesforce deployments and package development.",
    "properties": {
      "FullName": {
        "type": "string",
        "description": "The unique identifier for this metadata component",
        "nullable": false,
        "readOnly": false
      },
      "customButtons": {
        "type": "array",
        "itemType": "string",
        "nullable": false,
        "description": "custom Buttons field of Layout metadata component."
      },
      "customConsoleComponents": {
        "type": "CustomConsoleComponents",
        "originalType": "CustomConsoleComponents",
        "nullable": true,
        "readOnly": false,
        "description": "custom Console Components field of Layout metadata component.",
        "schema": {
          "type": "object",
          "description": "CustomConsoleComponents complex type",
          "properties": {
            "primaryTabComponents": {
              "type": "PrimaryTabComponents",
              "originalType": "PrimaryTabComponents",
              "nullable": true,
              "readOnly": false,
              "description": "primary Tab Components field of CustomConsoleComponents metadata component.",
              "schema": {
                "type": "object",
                "description": "PrimaryTabComponents complex type",
                "properties": {
                  "containers": {
                    "type": "array",
                    "itemType": "Container",
                    "nullable": false,
                    "description": "containers field of PrimaryTabComponents metadata component.",
                    "items": {
                      "type": "object",
                      "description": "Container complex type",
                      "properties": {
                        "height": {
                          "type": "double",
                          "originalType": "number",
                          "nullable": true,
                          "readOnly": false,
                          "description": "height field of Container metadata component."
                        },
                        "isContainerAutoSizeEnabled": {
                          "type": "boolean",
                          "originalType": "boolean",
                          "nullable": false,
                          "readOnly": false,
                          "description": "is Container Auto Size Enabled field of Container metadata component."
                        },
                        "region": {
                          "type": "string",
                          "originalType": "string",
                          "nullable": false,
                          "readOnly": false,
                          "description": "region field of Container metadata component."
                        },
                        "sidebarComponents": {
                          "type": "array",
                          "itemType": "SidebarComponent",
                          "nullable": false,
                          "description": "sidebar Components field of Container metadata component.",
                          "items": {
                            "$ref": "SidebarComponent"
                          }
                        },
                        "style": {
                          "type": "string",
                          "originalType": "string",
                          "nullable": false,
                          "readOnly": false,
                          "description": "style field of Container metadata component."
                        },
                        "unit": {
                          "type": "string",
                          "originalType": "string",
                          "nullable": false,
                          "readOnly": false,
                          "description": "unit field of Container metadata component."
                        },
                        "width": {
                          "type": "double",
                          "originalType": "number",
                          "nullable": true,
                          "readOnly": false,
                          "description": "width field of Container metadata component."
                        }
                      }
                    }
                  }
                }
              }
            },
            "subtabComponents": {
              "type": "SubtabComponents",
              "originalType": "SubtabComponents",
              "nullable": true,
              "readOnly": false,
              "description": "subtab Components field of CustomConsoleComponents metadata component.",
              "schema": {
                "type": "object",
                "description": "SubtabComponents complex type",
                "properties": {
                  "containers": {
                    "type": "array",
                    "itemType": "Container",
                    "nullable": false,
                    "description": "containers field of SubtabComponents metadata component.",
                    "items": {
                      "type": "object",
                      "description": "Container complex type",
                      "properties": {
                        "height": {
                          "type": "double",
                          "originalType": "number",
                          "nullable": true,
                          "readOnly": false,
                          "description": "height field of Container metadata component."
                        },
                        "isContainerAutoSizeEnabled": {
                          "type": "boolean",
                          "originalType": "boolean",
                          "nullable": false,
                          "readOnly": false,
                          "description": "is Container Auto Size Enabled field of Container metadata component."
                        },
                        "region": {
                          "type": "string",
                          "originalType": "string",
                          "nullable": false,
                          "readOnly": false,
                          "description": "region field of Container metadata component."
                        },
                        "sidebarComponents": {
                          "type": "array",
                          "itemType": "SidebarComponent",
                          "nullable": false,
                          "description": "sidebar Components field of Container metadata component.",
                          "items": {
                            "$ref": "SidebarComponent"
                          }
                        },
                        "style": {
                          "type": "string",
                          "originalType": "string",
                          "nullable": false,
                          "readOnly": false,
                          "description": "style field of Container metadata component."
                        },
                        "unit": {
                          "type": "string",
                          "originalType": "string",
                          "nullable": false,
                          "readOnly": false,
                          "description": "unit field of Container metadata component."
                        },
                        "width": {
                          "type": "double",
                          "originalType": "number",
                          "nullable": true,
                          "readOnly": false,
                          "description": "width field of Container metadata component."
                        }
                      }
                    }
                  }
                }
              }
            }
          }
        }
      },
      "emailDefault": {
        "type": "boolean",
        "originalType": "boolean",
        "nullable": true,
        "readOnly": false,
        "description": "email Default field of Layout metadata component."
      },
      "excludeButtons": {
        "type": "array",
        "itemType": "string",
        "nullable": false,
        "description": "exclude Buttons field of Layout metadata component."
      },
      "feedLayout": {
        "type": "FeedLayout",
        "originalType": "FeedLayout",
        "nullable": true,
        "readOnly": false,
        "description": "feed Layout field of Layout metadata component.",
        "schema": {
          "type": "object",
          "description": "FeedLayout complex type",
          "properties": {
            "autocollapsePublisher": {
              "type": "boolean",
              "originalType": "boolean",
              "nullable": true,
              "readOnly": false,
              "description": "autocollapse Publisher field of FeedLayout metadata component."
            },
            "compactFeed": {
              "type": "boolean",
              "originalType": "boolean",
              "nullable": true,
              "readOnly": false,
              "description": "compact Feed field of FeedLayout metadata component."
            },
            "feedFilterPosition": {
              "type": "string",
              "originalType": "string",
              "nullable": true,
              "readOnly": false,
              "description": "feed Filter Position field of FeedLayout metadata component."
            },
            "feedFilters": {
              "type": "array",
              "itemType": "FeedLayoutFilter",
              "nullable": false,
              "description": "feed Filters field of FeedLayout metadata component.",
              "items": {
                "type": "object",
                "description": "FeedLayoutFilter complex type",
                "properties": {
                  "feedFilterName": {
                    "type": "string",
                    "originalType": "string",
                    "nullable": true,
                    "readOnly": false,
                    "description": "feed Filter Name field of FeedLayoutFilter metadata component."
                  },
                  "feedFilterType": {
                    "type": "string",
                    "originalType": "string",
                    "nullable": false,
                    "readOnly": false,
                    "description": "feed Filter Type field of FeedLayoutFilter metadata component."
                  },
                  "feedItemType": {
                    "type": "string",
                    "originalType": "string",
                    "nullable": true,
                    "readOnly": false,
                    "description": "feed Item Type field of FeedLayoutFilter metadata component."
                  }
                }
              }
            },
            "fullWidthFeed": {
              "type": "boolean",
              "originalType": "boolean",
              "nullable": true,
              "readOnly": false,
              "description": "full Width Feed field of FeedLayout metadata component."
            },
            "hideSidebar": {
              "type": "boolean",
              "originalType": "boolean",
              "nullable": true,
              "readOnly": false,
              "description": "hide Sidebar field of FeedLayout metadata component."
            },
            "highlightExternalFeedItems": {
              "type": "boolean",
              "originalType": "boolean",
              "nullable": true,
              "readOnly": false,
              "description": "highlight External Feed Items field of FeedLayout metadata component."
            },
            "leftComponents": {
              "type": "array",
              "itemType": "FeedLayoutComponent",
              "nullable": false,
              "description": "left Components field of FeedLayout metadata component.",
              "items": {
                "type": "object",
                "description": "FeedLayoutComponent complex type",
                "properties": {
                  "componentType": {
                    "type": "string",
                    "originalType": "string",
                    "nullable": false,
                    "readOnly": false,
                    "description": "component Type field of FeedLayoutComponent metadata component."
                  },
                  "height": {
                    "type": "double",
                    "originalType": "number",
                    "nullable": true,
                    "readOnly": false,
                    "description": "height field of FeedLayoutComponent metadata component."
                  },
                  "page": {
                    "type": "string",
                    "originalType": "string",
                    "nullable": true,
                    "readOnly": false,
                    "description": "page field of FeedLayoutComponent metadata component."
                  }
                }
              }
            },
            "rightComponents": {
              "type": "array",
              "itemType": "FeedLayoutComponent",
              "nullable": false,
              "description": "right Components field of FeedLayout metadata component.",
              "items": {
                "type": "object",
                "description": "FeedLayoutComponent complex type",
                "properties": {
                  "componentType": {
                    "type": "string",
                    "originalType": "string",
                    "nullable": false,
                    "readOnly": false,
                    "description": "component Type field of FeedLayoutComponent metadata component."
                  },
                  "height": {
                    "type": "double",
                    "originalType": "number",
                    "nullable": true,
                    "readOnly": false,
                    "description": "height field of FeedLayoutComponent metadata component."
                  },
                  "page": {
                    "type": "string",
                    "originalType": "string",
                    "nullable": true,
                    "readOnly": false,
                    "description": "page field of FeedLayoutComponent metadata component."
                  }
                }
              }
            },
            "useInlineFiltersInConsole": {
              "type": "boolean",
              "originalType": "boolean",
              "nullable": true,
              "readOnly": false,
              "description": "use Inline Filters In Console field of FeedLayout metadata component."
            }
          }
        }
      },
      "headers": {
        "type": "array",
        "itemType": "string",
        "nullable": false,
        "description": "headers field of Layout metadata component."
      },
      "layoutSections": {
        "type": "array",
        "itemType": "LayoutSection",
        "nullable": false,
        "description": "layout Sections field of Layout metadata component.",
        "items": {
          "type": "object",
          "description": "LayoutSection complex type",
          "properties": {
            "customLabel": {
              "type": "boolean",
              "originalType": "boolean",
              "nullable": true,
              "readOnly": false,
              "description": "custom Label field of LayoutSection metadata component."
            },
            "detailHeading": {
              "type": "boolean",
              "originalType": "boolean",
              "nullable": true,
              "readOnly": false,
              "description": "detail Heading field of LayoutSection metadata component."
            },
            "editHeading": {
              "type": "boolean",
              "originalType": "boolean",
              "nullable": true,
              "readOnly": false,
              "description": "edit Heading field of LayoutSection metadata component."
            },
            "label": {
              "type": "string",
              "originalType": "string",
              "nullable": true,
              "readOnly": false,
              "description": "label field of LayoutSection metadata component."
            },
            "layoutColumns": {
              "type": "array",
              "itemType": "LayoutColumn",
              "nullable": false,
              "description": "layout Columns field of LayoutSection metadata component.",
              "items": {
                "type": "object",
                "description": "LayoutColumn complex type",
                "properties": {
                  "layoutItems": {
                    "type": "array",
                    "itemType": "LayoutItem",
                    "nullable": false,
                    "description": "layout Items field of LayoutColumn metadata component.",
                    "items": {
                      "type": "object",
                      "description": "LayoutItem complex type",
                      "properties": {
                        "analyticsCloudComponent": {
                          "type": "AnalyticsCloudComponentLayoutItem",
                          "originalType": "AnalyticsCloudComponentLayoutItem",
                          "nullable": true,
                          "readOnly": false,
                          "description": "analytics Cloud Component field of LayoutItem metadata component.",
                          "schema": {
                            "$ref": "AnalyticsCloudComponentLayoutItem"
                          }
                        },
                        "behavior": {
                          "type": "string",
                          "originalType": "string",
                          "nullable": true,
                          "readOnly": false,
                          "description": "behavior field of LayoutItem metadata component."
                        },
                        "canvas": {
                          "type": "string",
                          "originalType": "string",
                          "nullable": true,
                          "readOnly": false,
                          "description": "canvas field of LayoutItem metadata component."
                        },
                        "component": {
                          "type": "string",
                          "originalType": "string",
                          "nullable": true,
                          "readOnly": false,
                          "description": "component field of LayoutItem metadata component."
                        },
                        "customLink": {
                          "type": "string",
                          "originalType": "string",
                          "nullable": true,
                          "readOnly": false,
                          "description": "custom Link field of LayoutItem metadata component."
                        },
                        "emptySpace": {
                          "type": "boolean",
                          "originalType": "boolean",
                          "nullable": true,
                          "readOnly": false,
                          "description": "empty Space field of LayoutItem metadata component."
                        },
                        "field": {
                          "type": "string",
                          "originalType": "string",
                          "nullable": true,
                          "readOnly": false,
                          "description": "field field of LayoutItem metadata component."
                        },
                        "height": {
                          "type": "double",
                          "originalType": "number",
                          "nullable": true,
                          "readOnly": false,
                          "description": "height field of LayoutItem metadata component."
                        },
                        "page": {
                          "type": "string",
                          "originalType": "string",
                          "nullable": true,
                          "readOnly": false,
                          "description": "page field of LayoutItem metadata component."
                        },
                        "reportChartComponent": {
                          "type": "ReportChartComponentLayoutItem",
                          "originalType": "ReportChartComponentLayoutItem",
                          "nullable": true,
                          "readOnly": false,
                          "description": "report Chart Component field of LayoutItem metadata component.",
                          "schema": {
                            "$ref": "ReportChartComponentLayoutItem"
                          }
                        },
                        "scontrol": {
                          "type": "string",
                          "originalType": "string",
                          "nullable": true,
                          "readOnly": false,
                          "description": "scontrol field of LayoutItem metadata component."
                        },
                        "showLabel": {
                          "type": "boolean",
                          "originalType": "boolean",
                          "nullable": true,
                          "readOnly": false,
                          "description": "show Label field of LayoutItem metadata component."
                        },
                        "showScrollbars": {
                          "type": "boolean",
                          "originalType": "boolean",
                          "nullable": true,
                          "readOnly": false,
                          "description": "show Scrollbars field of LayoutItem metadata component."
                        },
                        "width": {
                          "type": "string",
                          "originalType": "string",
                          "nullable": true,
                          "readOnly": false,
                          "description": "width field of LayoutItem metadata component."
                        }
                      }
                    }
                  },
                  "reserved": {
                    "type": "string",
                    "originalType": "string",
                    "nullable": true,
                    "readOnly": false,
                    "description": "reserved field of LayoutColumn metadata component."
                  }
                }
              }
            },
            "style": {
              "type": "string",
              "originalType": "string",
              "nullable": false,
              "readOnly": false,
              "description": "style field of LayoutSection metadata component."
            }
          }
        }
      },
      "miniLayout": {
        "type": "MiniLayout",
        "originalType": "MiniLayout",
        "nullable": true,
        "readOnly": false,
        "description": "mini Layout field of Layout metadata component.",
        "schema": {
          "type": "object",
          "description": "MiniLayout complex type",
          "properties": {
            "fields": {
              "type": "array",
              "itemType": "string",
              "nullable": false,
              "description": "fields field of MiniLayout metadata component."
            },
            "relatedLists": {
              "type": "array",
              "itemType": "RelatedListItem",
              "nullable": false,
              "description": "related Lists field of MiniLayout metadata component.",
              "items": {
                "type": "object",
                "description": "RelatedListItem complex type",
                "properties": {
                  "customButtons": {
                    "type": "array",
                    "itemType": "string",
                    "nullable": false,
                    "description": "custom Buttons field of RelatedListItem metadata component."
                  },
                  "excludeButtons": {
                    "type": "array",
                    "itemType": "string",
                    "nullable": false,
                    "description": "exclude Buttons field of RelatedListItem metadata component."
                  },
                  "fields": {
                    "type": "array",
                    "itemType": "string",
                    "nullable": false,
                    "description": "fields field of RelatedListItem metadata component."
                  },
                  "relatedList": {
                    "type": "string",
                    "originalType": "string",
                    "nullable": false,
                    "readOnly": false,
                    "description": "related List field of RelatedListItem metadata component."
                  },
                  "sortField": {
                    "type": "string",
                    "originalType": "string",
                    "nullable": true,
                    "readOnly": false,
                    "description": "sort Field field of RelatedListItem metadata component."
                  },
                  "sortOrder": {
                    "type": "string",
                    "originalType": "string",
                    "nullable": true,
                    "readOnly": false,
                    "description": "sort Order field of RelatedListItem metadata component."
                  }
                }
              }
            }
          }
        }
      },
      "multilineLayoutFields": {
        "type": "array",
        "itemType": "string",
        "nullable": false,
        "description": "multiline Layout Fields field of Layout metadata component."
      },
      "platformActionList": {
        "type": "PlatformActionList",
        "originalType": "PlatformActionList",
        "nullable": true,
        "readOnly": false,
        "description": "platform Action List field of Layout metadata component.",
        "schema": {
          "type": "object",
          "description": "PlatformActionList complex type",
          "properties": {
            "fullName": {
              "type": "string",
              "originalType": "string",
              "nullable": true,
              "readOnly": false,
              "description": "full Name field of Metadata metadata component."
            },
            "actionListContext": {
              "type": "string",
              "originalType": "string",
              "nullable": false,
              "readOnly": false,
              "description": "action List Context field of PlatformActionList metadata component."
            },
            "platformActionListItems": {
              "type": "array",
              "itemType": "PlatformActionListItem",
              "nullable": false,
              "description": "platform Action List Items field of PlatformActionList metadata component.",
              "items": {
                "type": "object",
                "description": "PlatformActionListItem complex type",
                "properties": {
                  "actionName": {
                    "type": "string",
                    "originalType": "string",
                    "nullable": false,
                    "readOnly": false,
                    "description": "action Name field of PlatformActionListItem metadata component."
                  },
                  "actionType": {
                    "type": "string",
                    "originalType": "string",
                    "nullable": false,
                    "readOnly": false,
                    "description": "action Type field of PlatformActionListItem metadata component."
                  },
                  "sortOrder": {
                    "type": "double",
                    "originalType": "number",
                    "nullable": false,
                    "readOnly": false,
                    "description": "sort Order field of PlatformActionListItem metadata component."
                  },
                  "subtype": {
                    "type": "string",
                    "originalType": "string",
                    "nullable": true,
                    "readOnly": false,
                    "description": "subtype field of PlatformActionListItem metadata component."
                  }
                }
              }
            },
            "relatedSourceEntity": {
              "type": "string",
              "originalType": "string",
              "nullable": true,
              "readOnly": false,
              "description": "related Source Entity field of PlatformActionList metadata component."
            }
          }
        }
      },
      "quickActionList": {
        "type": "QuickActionList",
        "originalType": "QuickActionList",
        "nullable": true,
        "readOnly": false,
        "description": "quick Action List field of Layout metadata component.",
        "schema": {
          "type": "object",
          "description": "QuickActionList complex type",
          "properties": {
            "quickActionListItems": {
              "type": "array",
              "itemType": "QuickActionListItem",
              "nullable": false,
              "description": "quick Action List Items field of QuickActionList metadata component.",
              "items": {
                "type": "object",
                "description": "QuickActionListItem complex type",
                "properties": {
                  "quickActionName": {
                    "type": "string",
                    "originalType": "string",
                    "nullable": false,
                    "readOnly": false,
                    "description": "quick Action Name field of QuickActionListItem metadata component."
                  }
                }
              }
            }
          }
        }
      },
      "relatedContent": {
        "type": "RelatedContent",
        "originalType": "RelatedContent",
        "nullable": true,
        "readOnly": false,
        "description": "related Content field of Layout metadata component.",
        "schema": {
          "type": "object",
          "description": "RelatedContent complex type",
          "properties": {
            "relatedContentItems": {
              "type": "array",
              "itemType": "RelatedContentItem",
              "nullable": false,
              "description": "related Content Items field of RelatedContent metadata component.",
              "items": {
                "type": "object",
                "description": "RelatedContentItem complex type",
                "properties": {
                  "layoutItem": {
                    "type": "LayoutItem",
                    "originalType": "LayoutItem",
                    "nullable": false,
                    "readOnly": false,
                    "description": "layout Item field of RelatedContentItem metadata component.",
                    "schema": {
                      "type": "object",
                      "description": "LayoutItem complex type",
                      "properties": {
                        "analyticsCloudComponent": {
                          "type": "AnalyticsCloudComponentLayoutItem",
                          "originalType": "AnalyticsCloudComponentLayoutItem",
                          "nullable": true,
                          "readOnly": false,
                          "description": "analytics Cloud Component field of LayoutItem metadata component.",
                          "schema": {
                            "$ref": "AnalyticsCloudComponentLayoutItem"
                          }
                        },
                        "behavior": {
                          "type": "string",
                          "originalType": "string",
                          "nullable": true,
                          "readOnly": false,
                          "description": "behavior field of LayoutItem metadata component."
                        },
                        "canvas": {
                          "type": "string",
                          "originalType": "string",
                          "nullable": true,
                          "readOnly": false,
                          "description": "canvas field of LayoutItem metadata component."
                        },
                        "component": {
                          "type": "string",
                          "originalType": "string",
                          "nullable": true,
                          "readOnly": false,
                          "description": "component field of LayoutItem metadata component."
                        },
                        "customLink": {
                          "type": "string",
                          "originalType": "string",
                          "nullable": true,
                          "readOnly": false,
                          "description": "custom Link field of LayoutItem metadata component."
                        },
                        "emptySpace": {
                          "type": "boolean",
                          "originalType": "boolean",
                          "nullable": true,
                          "readOnly": false,
                          "description": "empty Space field of LayoutItem metadata component."
                        },
                        "field": {
                          "type": "string",
                          "originalType": "string",
                          "nullable": true,
                          "readOnly": false,
                          "description": "field field of LayoutItem metadata component."
                        },
                        "height": {
                          "type": "double",
                          "originalType": "number",
                          "nullable": true,
                          "readOnly": false,
                          "description": "height field of LayoutItem metadata component."
                        },
                        "page": {
                          "type": "string",
                          "originalType": "string",
                          "nullable": true,
                          "readOnly": false,
                          "description": "page field of LayoutItem metadata component."
                        },
                        "reportChartComponent": {
                          "type": "ReportChartComponentLayoutItem",
                          "originalType": "ReportChartComponentLayoutItem",
                          "nullable": true,
                          "readOnly": false,
                          "description": "report Chart Component field of LayoutItem metadata component.",
                          "schema": {
                            "$ref": "ReportChartComponentLayoutItem"
                          }
                        },
                        "scontrol": {
                          "type": "string",
                          "originalType": "string",
                          "nullable": true,
                          "readOnly": false,
                          "description": "scontrol field of LayoutItem metadata component."
                        },
                        "showLabel": {
                          "type": "boolean",
                          "originalType": "boolean",
                          "nullable": true,
                          "readOnly": false,
                          "description": "show Label field of LayoutItem metadata component."
                        },
                        "showScrollbars": {
                          "type": "boolean",
                          "originalType": "boolean",
                          "nullable": true,
                          "readOnly": false,
                          "description": "show Scrollbars field of LayoutItem metadata component."
                        },
                        "width": {
                          "type": "string",
                          "originalType": "string",
                          "nullable": true,
                          "readOnly": false,
                          "description": "width field of LayoutItem metadata component."
                        }
                      }
                    }
                  }
                }
              }
            }
          }
        }
      },
      "relatedLists": {
        "type": "array",
        "itemType": "RelatedListItem",
        "nullable": false,
        "description": "related Lists field of Layout metadata component.",
        "items": {
          "type": "object",
          "description": "RelatedListItem complex type",
          "properties": {
            "customButtons": {
              "type": "array",
              "itemType": "string",
              "nullable": false,
              "description": "custom Buttons field of RelatedListItem metadata component."
            },
            "excludeButtons": {
              "type": "array",
              "itemType": "string",
              "nullable": false,
              "description": "exclude Buttons field of RelatedListItem metadata component."
            },
            "fields": {
              "type": "array",
              "itemType": "string",
              "nullable": false,
              "description": "fields field of RelatedListItem metadata component."
            },
            "relatedList": {
              "type": "string",
              "originalType": "string",
              "nullable": false,
              "readOnly": false,
              "description": "related List field of RelatedListItem metadata component."
            },
            "sortField": {
              "type": "string",
              "originalType": "string",
              "nullable": true,
              "readOnly": false,
              "description": "sort Field field of RelatedListItem metadata component."
            },
            "sortOrder": {
              "type": "string",
              "originalType": "string",
              "nullable": true,
              "readOnly": false,
              "description": "sort Order field of RelatedListItem metadata component."
            }
          }
        }
      },
      "relatedObjects": {
        "type": "array",
        "itemType": "string",
        "nullable": false,
        "description": "related Objects field of Layout metadata component."
      },
      "runAssignmentRulesDefault": {
        "type": "boolean",
        "originalType": "boolean",
        "nullable": true,
        "readOnly": false,
        "description": "run Assignment Rules Default field of Layout metadata component."
      },
      "showEmailCheckbox": {
        "type": "boolean",
        "originalType": "boolean",
        "nullable": true,
        "readOnly": false,
        "description": "show Email Checkbox field of Layout metadata component."
      },
      "showHighlightsPanel": {
        "type": "boolean",
        "originalType": "boolean",
        "nullable": true,
        "readOnly": false,
        "description": "show Highlights Panel field of Layout metadata component."
      },
      "showInteractionLogPanel": {
        "type": "boolean",
        "originalType": "boolean",
        "nullable": true,
        "readOnly": false,
        "description": "show Interaction Log Panel field of Layout metadata component."
      },
      "showKnowledgeComponent": {
        "type": "boolean",
        "originalType": "boolean",
        "nullable": true,
        "readOnly": false,
        "description": "show Knowledge Component field of Layout metadata component."
      },
      "showRunAssignmentRulesCheckbox": {
        "type": "boolean",
        "originalType": "boolean",
        "nullable": true,
        "readOnly": false,
        "description": "show Run Assignment Rules Checkbox field of Layout metadata component."
      },
      "showSolutionSection": {
        "type": "boolean",
        "originalType": "boolean",
        "nullable": true,
        "readOnly": false,
        "description": "show Solution Section field of Layout metadata component."
      },
      "showSubmitAndAttachButton": {
        "type": "boolean",
        "originalType": "boolean",
        "nullable": true,
        "readOnly": false,
        "description": "show Submit And Attach Button field of Layout metadata component."
      },
      "summaryLayout": {
        "type": "SummaryLayout",
        "originalType": "SummaryLayout",
        "nullable": true,
        "readOnly": false,
        "description": "summary Layout field of Layout metadata component.",
        "schema": {
          "type": "object",
          "description": "SummaryLayout complex type",
          "properties": {
            "masterLabel": {
              "type": "string",
              "originalType": "string",
              "nullable": false,
              "readOnly": false,
              "description": "master Label field of SummaryLayout metadata component."
            },
            "sizeX": {
              "type": "double",
              "originalType": "number",
              "nullable": false,
              "readOnly": false,
              "description": "size X field of SummaryLayout metadata component."
            },
            "sizeY": {
              "type": "double",
              "originalType": "number",
              "nullable": true,
              "readOnly": false,
              "description": "size Y field of SummaryLayout metadata component."
            },
            "sizeZ": {
              "type": "double",
              "originalType": "number",
              "nullable": true,
              "readOnly": false,
              "description": "size Z field of SummaryLayout metadata component."
            },
            "summaryLayoutItems": {
              "type": "array",
              "itemType": "SummaryLayoutItem",
              "nullable": false,
              "description": "summary Layout Items field of SummaryLayout metadata component.",
              "items": {
                "type": "object",
                "description": "SummaryLayoutItem complex type",
                "properties": {
                  "customLink": {
                    "type": "string",
                    "originalType": "string",
                    "nullable": true,
                    "readOnly": false,
                    "description": "custom Link field of SummaryLayoutItem metadata component."
                  },
                  "field": {
                    "type": "string",
                    "originalType": "string",
                    "nullable": true,
                    "readOnly": false,
                    "description": "field field of SummaryLayoutItem metadata component."
                  },
                  "posX": {
                    "type": "double",
                    "originalType": "number",
                    "nullable": false,
                    "readOnly": false,
                    "description": "pos X field of SummaryLayoutItem metadata component."
                  },
                  "posY": {
                    "type": "double",
                    "originalType": "number",
                    "nullable": true,
                    "readOnly": false,
                    "description": "pos Y field of SummaryLayoutItem metadata component."
                  },
                  "posZ": {
                    "type": "double",
                    "originalType": "number",
                    "nullable": true,
                    "readOnly": false,
                    "description": "pos Z field of SummaryLayoutItem metadata component."
                  }
                }
              }
            },
            "summaryLayoutStyle": {
              "type": "string",
              "originalType": "string",
              "nullable": false,
              "readOnly": false,
              "description": "summary Layout Style field of SummaryLayout metadata component."
            }
          }
        }
      }
    },
    "module": "Metadata API",
    "extends": "Metadata"
  }
}