{
  "PricebookEntryAdjustment": {
    "name": "PricebookEntryAdjustment",
    "description": "Read-only junction object created when you associate a price adjustment schedule with a price book entry.",
    "properties": {
      "Name": {
        "type": "string",
        "description": "For internal use only."
      },
      "PriceAdjustmentScheduleId": {
        "type": "reference",
        "description": "The ID of the price book entry adjustment."
      },
      "PricebookEntryId": {
        "type": "reference",
        "description": "The ID of the price book entry that this price book entry adjustment is associated with."
      }
    },
    "module": "Core Salesforce",
    "sourceUrl": "https://developer.salesforce.com/docs/atlas.en-us.object_reference.meta/object_reference/sforce_api_objects_pricebookentryadjustment.htm"
  }
}