{
  "WebToCaseSettings": {
    "name": "WebToCaseSettings",
    "label": "Web To Case Settings",
    "description": "Represents WebToCaseSettings metadata component used in Salesforce deployments and package development.",
    "properties": {
      "FullName": {
        "type": "string",
        "description": "The unique identifier for this metadata component",
        "nullable": false,
        "readOnly": false
      },
      "caseOrigin": {
        "type": "string",
        "originalType": "string",
        "nullable": true,
        "readOnly": false,
        "description": "case Origin field of WebToCaseSettings metadata component."
      },
      "defaultResponseTemplate": {
        "type": "string",
        "originalType": "string",
        "nullable": true,
        "readOnly": false,
        "description": "default Response Template field of WebToCaseSettings metadata component."
      },
      "enableWebToCase": {
        "type": "boolean",
        "originalType": "boolean",
        "nullable": true,
        "readOnly": false,
        "description": "enable Web To Case field of WebToCaseSettings metadata component."
      }
    },
    "module": "Metadata API"
  }
}