{
  "FinServ_FinancialAccountTransaction__c": {
    "name": "FinServ_FinancialAccountTransaction__c",
    "description": "Represents information about a single financial account transaction.",
    "properties": {
      "AllocatedEscrowPayment__c": {
        "type": "currency",
        "description": "The amount of the payment that's allocated towards escrow."
      },
      "AllocatedFeeAmount__c": {
        "type": "currency",
        "description": "The amount of the payment that's allocated towards fees."
      },
      "AllocatedInterestAmount__c": {
        "type": "currency",
        "description": "The amount of the payment that's allocated towards the interest."
      },
      "AllocatedPrincipalAmount__c": {
        "type": "currency",
        "description": "The amount of the payment that's allocated towards the principal."
      },
      "Amount__c": {
        "type": "currency",
        "description": "Amount of the transaction."
      },
      "BillingStatement__c": {
        "type": "reference",
        "description": "Billing statement record associated with the account."
      },
      "CardAccountID__c": {
        "type": "string",
        "description": "Card number linked to the transaction."
      },
      "Claim__c": {
        "type": "reference",
        "description": "The claim associated with the financial account transaction."
      },
      "Description__c": {
        "type": "string",
        "description": "Description of the transaction."
      },
      "DisputeReason__c": {
        "type": "picklist",
        "description": "Reason for the dispute."
      },
      "EscrowBalance__c": {
        "type": "currency",
        "description": "The balance on the escrow amount of the financial account."
      },
      "FinancialAccount__c": {
        "type": "reference",
        "description": "Financial account to which the transaction pertains."
      },
      "InsurancePolicy__c": {
        "type": "reference",
        "description": "The insurance policy associated with the financial account transaction."
      },
      "MerchantCategoryCode__c": {
        "type": "string",
        "description": "Merchant category code."
      },
      "PostDate__c": {
        "type": "dateTime",
        "description": "Date the transaction posted to the account."
      },
      "PrincipalBalance__c": {
        "type": "currency",
        "description": "The balance on the principal amount of the financial account."
      },
      "RunningBalance__c": {
        "type": "currency",
        "description": "Running balance for the transaction."
      },
      "SourceSystemId__c": {
        "type": "string",
        "description": "Record ID from an external data source."
      },
      "SourceTransactionType__c": {
        "type": "string",
        "description": "Source transaction type from an external data source."
      },
      "TransactionDate__c": {
        "type": "dateTime",
        "description": "Date of the transaction."
      },
      "TransactionId__c": {
        "type": "string",
        "description": "ID that uniquely identifies the transaction in an external data source."
      },
      "TransactionStatus__c": {
        "type": "picklist",
        "description": "Status of the transaction. Pending Posted"
      },
      "TransactionType__c": {
        "type": "picklist",
        "description": "Type of transaction. Credit Debit"
      }
    },
    "module": "Financial Services Cloud",
    "sourceUrl": "https://developer.salesforce.com/docs/atlas.en-us.financial_services_cloud_object_reference.meta/financial_services_cloud_object_reference/sforce_api_objects_financialaccounttransaction.htm"
  }
}