{
  "CommunityTemplateDefinition": {
    "name": "CommunityTemplateDefinition",
    "label": "Community Template Definition",
    "description": "Represents CommunityTemplateDefinition metadata component used in Salesforce deployments and package development.",
    "properties": {
      "FullName": {
        "type": "string",
        "description": "The unique identifier for this metadata component",
        "nullable": false,
        "readOnly": false
      },
      "baseTemplate": {
        "type": "string",
        "originalType": "string",
        "nullable": true,
        "readOnly": false,
        "description": "base Template field of CommunityTemplateDefinition metadata component."
      },
      "bundlesInfo": {
        "type": "array",
        "itemType": "CommunityTemplateBundleInfo",
        "nullable": false,
        "description": "bundles Info field of CommunityTemplateDefinition metadata component.",
        "items": {
          "type": "object",
          "description": "CommunityTemplateBundleInfo complex type",
          "properties": {
            "description": {
              "type": "string",
              "originalType": "string",
              "nullable": true,
              "readOnly": false,
              "description": "description field of CommunityTemplateBundleInfo metadata component."
            },
            "image": {
              "type": "string",
              "originalType": "string",
              "nullable": true,
              "readOnly": false,
              "description": "image field of CommunityTemplateBundleInfo metadata component."
            },
            "order": {
              "type": "double",
              "originalType": "number",
              "nullable": false,
              "readOnly": false,
              "description": "order field of CommunityTemplateBundleInfo metadata component."
            },
            "title": {
              "type": "string",
              "originalType": "string",
              "nullable": false,
              "readOnly": false,
              "description": "title field of CommunityTemplateBundleInfo metadata component."
            },
            "type": {
              "type": "string",
              "originalType": "string",
              "nullable": false,
              "readOnly": false,
              "description": "type field of CommunityTemplateBundleInfo metadata component."
            }
          }
        }
      },
      "category": {
        "type": "string",
        "originalType": "string",
        "nullable": false,
        "readOnly": false,
        "description": "category field of CommunityTemplateDefinition metadata component."
      },
      "defaultBrandingSet": {
        "type": "string",
        "originalType": "string",
        "nullable": true,
        "readOnly": false,
        "description": "default Branding Set field of CommunityTemplateDefinition metadata component."
      },
      "defaultThemeDefinition": {
        "type": "string",
        "originalType": "string",
        "nullable": false,
        "readOnly": false,
        "description": "default Theme Definition field of CommunityTemplateDefinition metadata component."
      },
      "description": {
        "type": "string",
        "originalType": "string",
        "nullable": true,
        "readOnly": false,
        "description": "description field of CommunityTemplateDefinition metadata component."
      },
      "enableExtendedCleanUpOnDelete": {
        "type": "boolean",
        "originalType": "boolean",
        "nullable": true,
        "readOnly": false,
        "description": "enable Extended Clean Up On Delete field of CommunityTemplateDefinition metadata component."
      },
      "masterLabel": {
        "type": "string",
        "originalType": "string",
        "nullable": false,
        "readOnly": false,
        "description": "master Label field of CommunityTemplateDefinition metadata component."
      },
      "navigationLinkSet": {
        "type": "array",
        "itemType": "NavigationLinkSet",
        "nullable": false,
        "description": "navigation Link Set field of CommunityTemplateDefinition metadata component.",
        "items": {
          "type": "object",
          "description": "NavigationLinkSet complex type",
          "properties": {
            "navigationMenuItem": {
              "type": "array",
              "itemType": "NavigationMenuItem",
              "nullable": false,
              "description": "navigation Menu Item field of NavigationLinkSet metadata component.",
              "items": {
                "type": "object",
                "description": "NavigationMenuItem complex type",
                "properties": {
                  "defaultListViewId": {
                    "type": "string",
                    "originalType": "string",
                    "nullable": true,
                    "readOnly": false,
                    "description": "default List View Id field of NavigationMenuItem metadata component."
                  },
                  "label": {
                    "type": "string",
                    "originalType": "string",
                    "nullable": false,
                    "readOnly": false,
                    "description": "label field of NavigationMenuItem metadata component."
                  },
                  "menuItemBranding": {
                    "type": "NavigationMenuItemBranding",
                    "originalType": "NavigationMenuItemBranding",
                    "nullable": true,
                    "readOnly": false,
                    "description": "menu Item Branding field of NavigationMenuItem metadata component.",
                    "schema": {
                      "type": "object",
                      "description": "NavigationMenuItemBranding complex type",
                      "properties": {
                        "tileImage": {
                          "type": "string",
                          "originalType": "string",
                          "nullable": true,
                          "readOnly": false,
                          "description": "tile Image field of NavigationMenuItemBranding metadata component."
                        }
                      }
                    }
                  },
                  "position": {
                    "type": "double",
                    "originalType": "number",
                    "nullable": false,
                    "readOnly": false,
                    "description": "position field of NavigationMenuItem metadata component."
                  },
                  "publiclyAvailable": {
                    "type": "boolean",
                    "originalType": "boolean",
                    "nullable": true,
                    "readOnly": false,
                    "description": "publicly Available field of NavigationMenuItem metadata component."
                  },
                  "subMenu": {
                    "type": "NavigationSubMenu",
                    "originalType": "NavigationSubMenu",
                    "nullable": true,
                    "readOnly": false,
                    "description": "sub Menu field of NavigationMenuItem metadata component.",
                    "schema": {
                      "type": "object",
                      "description": "NavigationSubMenu complex type",
                      "properties": {
                        "navigationMenuItem": {
                          "type": "array",
                          "itemType": "NavigationMenuItem",
                          "nullable": false,
                          "description": "navigation Menu Item field of NavigationSubMenu metadata component.",
                          "items": {
                            "$ref": "NavigationMenuItem"
                          }
                        }
                      }
                    }
                  },
                  "target": {
                    "type": "string",
                    "originalType": "string",
                    "nullable": true,
                    "readOnly": false,
                    "description": "target field of NavigationMenuItem metadata component."
                  },
                  "targetPreference": {
                    "type": "string",
                    "originalType": "string",
                    "nullable": true,
                    "readOnly": false,
                    "description": "target Preference field of NavigationMenuItem metadata component."
                  },
                  "type": {
                    "type": "string",
                    "originalType": "string",
                    "nullable": false,
                    "readOnly": false,
                    "description": "type field of NavigationMenuItem metadata component."
                  }
                }
              }
            }
          }
        }
      },
      "pageSetting": {
        "type": "array",
        "itemType": "CommunityTemplatePageSetting",
        "nullable": false,
        "description": "page Setting field of CommunityTemplateDefinition metadata component.",
        "items": {
          "type": "object",
          "description": "CommunityTemplatePageSetting complex type",
          "properties": {
            "page": {
              "type": "string",
              "originalType": "string",
              "nullable": false,
              "readOnly": false,
              "description": "page field of CommunityTemplatePageSetting metadata component."
            },
            "themeLayout": {
              "type": "string",
              "originalType": "string",
              "nullable": false,
              "readOnly": false,
              "description": "theme Layout field of CommunityTemplatePageSetting metadata component."
            }
          }
        }
      },
      "publisher": {
        "type": "string",
        "originalType": "string",
        "nullable": true,
        "readOnly": false,
        "description": "publisher field of CommunityTemplateDefinition metadata component."
      }
    },
    "module": "Metadata API",
    "extends": "Metadata"
  }
}